consoil/Consolidation of double compressible layer v2.py
consoil/Numerical solution Gibson Equation.py
consoil/Znidarcic analytical solution v4.py
consoil/__init__.py
consoil/constants.py
consoil-0.0.1.dist-info/LICENSE
consoil-0.0.1.dist-info/METADATA
consoil-0.0.1.dist-info/WHEEL
consoil-0.0.1.dist-info/top_level.txt
consoil-0.0.1.dist-info/RECORD
