Metadata-Version: 2.1
Name: consoil
Version: 0.0.1
Summary: Consolidation and Sedimentation software in Python
Author-email: Ismail Myouri <i.myouri@tudelft.nl>
Project-URL: Homepage, https://bitbucket.org/deltares/consoil/
Classifier: Programming Language :: Python :: 3
Classifier: License :: OSI Approved :: GNU General Public License v3 or later (GPLv3+)
Classifier: Operating System :: OS Independent
Requires-Python: >=3.11
License-File: LICENSE
